postman_sdk/__init__.py
postman_sdk/exceptions/__init__.py
postman_sdk/instrumentor/__init__.py
postman_sdk/instrumentor/base_instrumentation/__init__.py
postman_sdk/instrumentor/postman_flask_instrumentation/__init__.py
postman_sdk/instrumentor/postman_requests_instrumentation/__init__.py
postman_sdk/model/__init__.py
postman_sdk/model/base_config.py
postman_sdk/model/data_redaction.py
postman_sdk/model/dynamic_model.py
postman_sdk/model/http.py
postman_sdk/model/semantic_attributes.py
postman_sdk/plugins/__init__.py
postman_sdk/plugins/data_redaction.py
postman_sdk/plugins/data_truncation.py
postman_sdk/postman_otel/__init__.py
postman_sdk/postman_otel/postman_exporter.py
postman_sdk/postman_otel/postman_span_processor.py
postman_sdk/postman_otel/postman_tracer.py
postman_sdk/receiver_service/__init__.py
postman_sdk/receiver_service/bootstrap.py
postman_sdk/receiver_service/client.py
postman_sdk/receiver_service/config.py
postman_sdk/receiver_service/health_check.py
postman_sdk/util/__init__.py
postman_sdk/util/constants.py
postman_sdk/util/helper.py
postman_sdk/util/logger.py
postman_sdk-0.0.12.dist-info/LICENSE.md
postman_sdk-0.0.12.dist-info/METADATA
postman_sdk-0.0.12.dist-info/WHEEL
postman_sdk-0.0.12.dist-info/top_level.txt
postman_sdk-0.0.12.dist-info/RECORD
