Metadata-Version: 2.1
Name: postman-sdk
Version: 0.0.12
Summary: Postman SDK
Classifier: Programming Language :: Python :: 3
Classifier: Operating System :: OS Independent
Requires-Python: >=3.7
License-File: LICENSE.md
Requires-Dist: Deprecated (==1.2.13)
Requires-Dist: googleapis-common-protos (==1.58.0)
Requires-Dist: loguru (==0.6.0)
Requires-Dist: opentelemetry-api (==1.16.0)
Requires-Dist: opentelemetry-exporter-otlp (==1.16.0)
Requires-Dist: opentelemetry-exporter-otlp-proto-grpc (==1.16.0)
Requires-Dist: opentelemetry-exporter-otlp-proto-http (==1.16.0)
Requires-Dist: opentelemetry-instrumentation (==0.37b0)
Requires-Dist: opentelemetry-instrumentation-flask (==0.37b0)
Requires-Dist: opentelemetry-instrumentation-requests (==0.37b0)
Requires-Dist: opentelemetry-instrumentation-wsgi (==0.37b0)
Requires-Dist: opentelemetry-proto (==1.16.0)
Requires-Dist: opentelemetry-sdk (==1.16.0)
Requires-Dist: opentelemetry-semantic-conventions (==0.37b0)
Requires-Dist: opentelemetry-util-http (==0.37b0)
Requires-Dist: protobuf (==4.22.1)
Requires-Dist: pydantic (==1.10.6)
Requires-Dist: requests (>2.0.0)
Requires-Dist: wrapt (~=1.15.0)
